files/__init__.py
files/functions.py
files/interfaz.py
pdf2wordx23456ldfpodfdfdfkdf-2.1.0.dist-info/licenses/LICENSE
pdf2wordx23456ldfpodfdfdfkdf-2.1.0.dist-info/METADATA
pdf2wordx23456ldfpodfdfdfkdf-2.1.0.dist-info/WHEEL
pdf2wordx23456ldfpodfdfdfkdf-2.1.0.dist-info/entry_points.txt
pdf2wordx23456ldfpodfdfdfkdf-2.1.0.dist-info/top_level.txt
pdf2wordx23456ldfpodfdfdfkdf-2.1.0.dist-info/RECORD
