Metadata-Version: 2.4
Name: pdf2wordx23456ldfpodfdfdfkdf
Version: 2.1.0
Summary: PDF to DOCX converter with UI
Author-email: Tutos Rive <tutosriveorg@gmail.com>
License-Expression: MIT
Project-URL: Homepage, https://tutosrive.github.io/pdf2wordx/
Project-URL: Repository, https://github.com/tutosrive/pdf2wordx/
Project-URL: YouTube, https://www.youtube.com/@tutosrive
Classifier: Development Status :: 5 - Production/Stable
Classifier: Intended Audience :: Developers
Classifier: Intended Audience :: Information Technology
Classifier: Intended Audience :: System Administrators
Classifier: Topic :: Software Development :: Libraries
Classifier: Topic :: Utilities
Classifier: Programming Language :: Python
Classifier: Programming Language :: Python :: 3.8
Classifier: Programming Language :: Python :: 3.9
Classifier: Programming Language :: Python :: 3.10
Classifier: Programming Language :: Python :: 3.11
Classifier: Programming Language :: Python :: 3.12
Classifier: Operating System :: OS Independent
Classifier: Environment :: Other Environment
Requires-Python: <3.13,>=3.8
License-File: LICENSE
Requires-Dist: chromologger<=0.1.9,>=0.1.4
Requires-Dist: pdf2docx==0.5.8
Dynamic: license-file
